find_title.py
web_title-0.1.dist-info/DESCRIPTION.rst
web_title-0.1.dist-info/METADATA
web_title-0.1.dist-info/RECORD
web_title-0.1.dist-info/WHEEL
web_title-0.1.dist-info/metadata.json
web_title-0.1.dist-info/top_level.txt
