Metadata-Version: 2.0
Name: web-title
Version: 0.1
Summary: Find web site title
Home-page: https://python-forum.io/index.php
Author: UNKNOWN
Author-email: something@python.io
License: UNKNOWN
Platform: UNKNOWN
Classifier: Programming Language :: Python :: 3.4
Classifier: Programming Language :: Python :: 3.5
Classifier: Programming Language :: Python :: 3.6
Requires-Python: >=3.4
Requires-Dist: beautifulsoup4
Requires-Dist: lxml
Requires-Dist: requests
